pid_tuner/cli.py
pid_tuner/compare.py
pid_tuner/parser.py
pid_tuner/plotter.py
pid_tuner/stats.py
pid_tuner-0.1.2.dist-info/licenses/LICENSE
pid_tuner-0.1.2.dist-info/METADATA
pid_tuner-0.1.2.dist-info/WHEEL
pid_tuner-0.1.2.dist-info/entry_points.txt
pid_tuner-0.1.2.dist-info/top_level.txt
pid_tuner-0.1.2.dist-info/RECORD
