Metadata-Version: 2.4
Name: pid-tuner
Version: 0.1.2
Summary: FPV PID Tuner CLI tools
Author: bMagSquatch
License: MIT License
Project-URL: Homepage, https://github.com/bmags73/pid-tuner
Project-URL: Repository, https://github.com/bmags73/pid-tuner
Keywords: fpv,drone,pid,analysis
Classifier: Programming Language :: Python :: 3
Classifier: License :: OSI Approved :: MIT License
Classifier: Operating System :: OS Independent
License-File: LICENSE
Requires-Dist: pandas
Requires-Dist: matplotlib
Requires-Dist: typer
Requires-Dist: click
Requires-Dist: shellingham
Requires-Dist: rich
Dynamic: license-file
